{
  "rust-analyzer.serverPath": "/usr/bin/rust-analyzer",
  "rust-analyzer.inlayHints.chainingHints": false,
  "languageserver": {
    "codeql" : {
      "command": "codeql",
      "args": [
        "execute",
        "language-server",
        "--check-errors=ON_CHANGE",
        "--search-path=/home/tunnelshade/workspace/codeql/codeql/:./",
        "-q"
      ],
      "filetypes": ["ql"],
      "rootPatterns": ["qlpack.yml"],
      "requireRootPattern": true
    },
    "ccls": {
      "command": "ccls",
      "filetypes": ["c", "cc", "cpp", "c++", "objc", "objcpp"],
      "rootPatterns": [".ccls", "compile_commands.json", ".git/", ".hg/"],
      "initializationOptions": {
        "cache": {
          "directory": "/tmp/ccls"
        }
      }
    }
  },
  "diagnostic-languageserver.filetypes": {
    "sh": "shellcheck"
  },
  "diagnostic-languageserver.formatFiletypes": {
    "sh": "shfmt"
  },
  "diagnostic-languageserver.formatters": {
    "shfmt": {
      "command": "shfmt",
      "args": ["-i", "2", "-bn", "-ci", "-sr"]
    }
  }
}
